vpype_ttf/ftext.py
vpype_ttf-0.0.7.dist-info/LICENSE
vpype_ttf-0.0.7.dist-info/METADATA
vpype_ttf-0.0.7.dist-info/WHEEL
vpype_ttf-0.0.7.dist-info/entry_points.txt
vpype_ttf-0.0.7.dist-info/top_level.txt
vpype_ttf-0.0.7.dist-info/RECORD
