Metadata-Version: 2.1
Name: vpype-ttf
Version: 0.0.7
Summary: vpype ttf plugin
Home-page: https://github.com/johnbentcope/vpype-ttf/
Author: John Cope
Author-email: johnbentcope@gmail.com
Classifier: Programming Language :: Python :: 3.7
Classifier: Programming Language :: Python :: 3.8
Classifier: Programming Language :: Python :: 3.9
Classifier: Programming Language :: Python :: 3.10
Classifier: Programming Language :: Python :: 3.11
Classifier: License :: OSI Approved :: MIT License
Classifier: Operating System :: OS Independent
License-File: LICENSE
Requires-Dist: click
Requires-Dist: vpype<2.0,>=1.9
Requires-Dist: numpy
Requires-Dist: freetype-py
